Metadata-Version: 1.0
Name: UD-oop-distributions
Version: 0.1
Summary: Gaussian and Binomial distributions
Home-page: UNKNOWN
Author: Riccardo Galli
Author-email: riccardomgalli@gmail.com
License: UNKNOWN
Platform: UNKNOWN
